wow_bis_rolls/__about__.py
wow_bis_rolls/__init__.py
wow_bis_rolls/rolls.py
wow_bis_rolls-0.0.1.dist-info/METADATA
wow_bis_rolls-0.0.1.dist-info/WHEEL
wow_bis_rolls-0.0.1.dist-info/entry_points.txt
wow_bis_rolls-0.0.1.dist-info/licenses/LICENSE.txt
wow_bis_rolls-0.0.1.dist-info/RECORD
