Metadata-Version: 2.4
Name: wow-bis-rolls
Version: 0.0.1
Summary: Finds all the BiS(101) rolls in a gargul json file
Project-URL: Documentation, https://github.com/byornski/wow-bis-rolls#readme
Project-URL: Issues, https://github.com/byornski/wow-bis-rolls/issues
Project-URL: Source, https://github.com/byornski/wow-bis-rolls
Author-email: byornski <byski@gmail.cm>
License-Expression: MIT
License-File: LICENSE.txt
Classifier: Development Status :: 4 - Beta
Classifier: Programming Language :: Python
Classifier: Programming Language :: Python :: 3.8
Classifier: Programming Language :: Python :: 3.9
Classifier: Programming Language :: Python :: 3.10
Classifier: Programming Language :: Python :: 3.11
Classifier: Programming Language :: Python :: 3.12
Classifier: Programming Language :: Python :: Implementation :: CPython
Classifier: Programming Language :: Python :: Implementation :: PyPy
Requires-Python: >=3.8
